<?xml version="1.0" encoding="UTF-8"?>
<monster name="Ghost" nameDescription="a ghost" race="undead" experience="0" speed="160" manacost="100">
	<health now="2000" max="2000"/>
	<look type="48" corpse="5993"/>
	<targetchange interval="4000" chance="0"/>
	<flags>
		<flag summonable="0"/>
		<flag attackable="1"/>
		<flag hostile="1"/>
		<flag illusionable="0"/>
		<flag convinceable="0"/>
		<flag pushable="0"/>
		<flag canpushitems="1"/>
		<flag canpushcreatures="0"/>
		<flag targetdistance="2"/>
		<flag staticattack="90"/>
		<flag runonhealth="0"/>
	</flags>
    
	
		<voice sentence="boo"/>
		<voice sentence="hue"/>
	
</monster>